openg2p_spar_self_service_api/__init__.py
openg2p_spar_self_service_api/app.py
openg2p_spar_self_service_api/config.py
openg2p_spar_self_service_api/controllers/__init__.py
openg2p_spar_self_service_api/controllers/dfsp_controller.py
openg2p_spar_self_service_api/controllers/selfservice_controller.py
openg2p_spar_self_service_api/helpers/__init__.py
openg2p_spar_self_service_api/helpers/response_helper.py
openg2p_spar_self_service_api/helpers/strategy_helper.py
openg2p_spar_self_service_api/models/__init__.py
openg2p_spar_self_service_api/models/dfsp.py
openg2p_spar_self_service_api/models/login_provider.py
openg2p_spar_self_service_api/models/strategy.py
openg2p_spar_self_service_api/schemas/__init__.py
openg2p_spar_self_service_api/schemas/dfsp.py
openg2p_spar_self_service_api/schemas/mapper.py
openg2p_spar_self_service_api/schemas/request.py
openg2p_spar_self_service_api/schemas/response.py
openg2p_spar_self_service_api-1.1.0.dist-info/METADATA
openg2p_spar_self_service_api-1.1.0.dist-info/WHEEL
openg2p_spar_self_service_api-1.1.0.dist-info/RECORD
